surfactant/__init__.py
surfactant/__main__.py
surfactant/_version.py
surfactant/configmanager.py
surfactant/context.py
surfactant/fileinfo.py
surfactant/cmd/cli.py
surfactant/cmd/config.py
surfactant/cmd/generate.py
surfactant/cmd/merge.py
surfactant/cmd/plugin.py
surfactant/cmd/stat.py
surfactant/cmd/tui.py
surfactant/cmd/cli_commands/__init__.py
surfactant/cmd/cli_commands/cli_base.py
surfactant/cmd/cli_commands/cli_load.py
surfactant/cmd/cli_commands/cli_save.py
surfactant/cmd/internal/generate_utils.py
surfactant/database_manager/__init__.py
surfactant/database_manager/database_utils.py
surfactant/database_manager/utils.py
surfactant/filetypeid/__init__.py
surfactant/filetypeid/id_extension.py
surfactant/filetypeid/id_hex.py
surfactant/filetypeid/id_magic.py
surfactant/infoextractors/__init__.py
surfactant/infoextractors/__macho_cpuSubtypes.py
surfactant/infoextractors/a_out_file.py
surfactant/infoextractors/coff_file.py
surfactant/infoextractors/docker_image.py
surfactant/infoextractors/elf_file.py
surfactant/infoextractors/file_decompression.py
surfactant/infoextractors/java_file.py
surfactant/infoextractors/js_file.py
surfactant/infoextractors/mach_o_file.py
surfactant/infoextractors/native_lib_file.py
surfactant/infoextractors/ole_file.py
surfactant/infoextractors/pe_file.py
surfactant/infoextractors/rpm_file.py
surfactant/infoextractors/uimage_file.py
surfactant/input_readers/__init__.py
surfactant/input_readers/cytrics_reader.py
surfactant/output/__init__.py
surfactant/output/csv_writer.py
surfactant/output/cyclonedx_writer.py
surfactant/output/cytrics_writer.py
surfactant/output/spdx_writer.py
surfactant/plugin/__init__.py
surfactant/plugin/hookspecs.py
surfactant/plugin/manager.py
surfactant/relationships/__init__.py
surfactant/relationships/dotnet_relationship.py
surfactant/relationships/elf_relationship.py
surfactant/relationships/java_relationship.py
surfactant/relationships/pe_relationship.py
surfactant/relationships/rpmfile_relationship.py
surfactant-0.0.0rc17.dist-info/licenses/LICENSE
surfactant-0.0.0rc17.dist-info/licenses/NOTICE
surfactant-0.0.0rc17.dist-info/METADATA
surfactant-0.0.0rc17.dist-info/WHEEL
surfactant-0.0.0rc17.dist-info/entry_points.txt
surfactant-0.0.0rc17.dist-info/top_level.txt
surfactant-0.0.0rc17.dist-info/RECORD
