Metadata-Version: 2.4
Name: Surfactant
Version: 0.0.0rc17
Summary: Modular framework to gather file information, analyze dependencies, and generate an SBOM
Author-email: Ryan Mast <mast9@llnl.gov>, Levi Lloyd <lloyd27@llnl.gov>, Micaela Gallegos <gallegos31@llnl.gov>, Alexander Armstrong <armstrong48@llnl.gov>, Shayna Kapadia <kapadia2@llnl.gov>, Asriel Margarian <margarian1@llnl.gov>, Matthew Kelley <kelley41@llnl.gov>
Maintainer-email: Ryan Mast <mast9@llnl.gov>
License-Expression: MIT
Project-URL: Homepage, https://github.com/LLNL/Surfactant
Project-URL: Discussions, https://github.com/LLNL/Surfactant/discussions
Project-URL: Documentation, https://surfactant.readthedocs.io/en/latest/
Project-URL: Issue Tracker, https://github.com/LLNL/Surfactant/issues
Project-URL: Source Code, https://github.com/LLNL/Surfactant
Keywords: sbom,pe,elf,ole,msi
Classifier: Programming Language :: Python :: 3
Classifier: Programming Language :: Python :: 3 :: Only
Classifier: Programming Language :: Python :: 3.10
Classifier: Programming Language :: Python :: 3.11
Classifier: Programming Language :: Python :: 3.12
Classifier: Programming Language :: Python :: 3.13
Classifier: Development Status :: 3 - Alpha
Classifier: Environment :: Console
Classifier: Operating System :: MacOS
Classifier: Operating System :: Microsoft :: Windows
Classifier: Operating System :: POSIX :: Linux
Classifier: Topic :: Security
Classifier: Topic :: Software Development
Classifier: Topic :: System
Classifier: Topic :: Utilities
Requires-Python: >=3.10
License-File: LICENSE
License-File: NOTICE
Requires-Dist: dataclasses_json==0.6.*
Requires-Dist: pyelftools==0.32.*
Requires-Dist: pefile==2024.8.26
Requires-Dist: dnfile==0.17.*
Requires-Dist: olefile==0.47.*
Requires-Dist: defusedxml==0.7.*
Requires-Dist: spdx-tools==0.8.*
Requires-Dist: cyclonedx-python-lib==11.6.0
Requires-Dist: pluggy==1.*
Requires-Dist: click==8.*
Requires-Dist: loguru==0.7.*
Requires-Dist: tomlkit==0.13.*
Requires-Dist: textual==7.*
Requires-Dist: requests>=2.32.3
Requires-Dist: rarfile==4.2.*
Requires-Dist: networkx>=2.6
Requires-Dist: regex; platform_python_implementation == "CPython"
Requires-Dist: python-msi==0.0.0b3
Requires-Dist: rpmfile==2.1.0
Provides-Extra: macho
Requires-Dist: lief==0.17.2; extra == "macho"
Provides-Extra: java
Requires-Dist: javatools==1.*,>=1.6; extra == "java"
Provides-Extra: test
Requires-Dist: pytest; extra == "test"
Requires-Dist: pytest-asyncio; extra == "test"
Provides-Extra: dev
Requires-Dist: build; extra == "dev"
Requires-Dist: pre-commit; extra == "dev"
Provides-Extra: docs
Requires-Dist: sphinx; extra == "docs"
Requires-Dist: myst-parser; extra == "docs"
Requires-Dist: furo>=2025.9.25; extra == "docs"
Requires-Dist: sphinx-copybutton>=0.5.2; extra == "docs"
Dynamic: license-file
